{
  "version": "16.0.0",
  "files": {
    "31aaccc40fff88e6b8aeb9d3e4d24daaa9117ff6d37a5185e582008cc150305f": {
      "source": {
        "path": "aurora-ml-pg.template.json",
        "packaging": "file"
      },
      "destinations": {
        "current_account-current_region": {
          "bucketName": "cdk-hnb659fds-assets-${AWS::AccountId}-${AWS::Region}",
          "objectKey": "31aaccc40fff88e6b8aeb9d3e4d24daaa9117ff6d37a5185e582008cc150305f.json",
          "assumeRoleArn": "arn:${AWS::Partition}:iam::${AWS::AccountId}:role/cdk-hnb659fds-file-publishing-role-${AWS::AccountId}-${AWS::Region}"
        }
      }
    }
  },
  "dockerImages": {}
}